bitstring/__init__.py
bitstring/__main__.py
bitstring/array_.py
bitstring/bitarray_.py
bitstring/bits.py
bitstring/bitstore.py
bitstring/bitstore_helpers.py
bitstring/bitstream.py
bitstring/bitstring_options.py
bitstring/dtypes.py
bitstring/exceptions.py
bitstring/fp8.py
bitstring/luts.py
bitstring/methods.py
bitstring/mxfp.py
bitstring/py.typed
bitstring/utils.py
bitstring-4.2.3.dist-info/LICENSE
bitstring-4.2.3.dist-info/METADATA
bitstring-4.2.3.dist-info/WHEEL
bitstring-4.2.3.dist-info/top_level.txt
bitstring-4.2.3.dist-info/RECORD
