Metadata-Version: 2.1
Name: bitstring
Version: 4.2.3
Summary: Simple construction, analysis and modification of binary data.
Author-email: Scott Griffiths <dr.scottgriffiths@gmail.com>
Project-URL: homepage, https://github.com/scott-griffiths/bitstring
Project-URL: documentation, https://bitstring.readthedocs.io/
Keywords: binary,bitarray,bitvector,bitfield
Classifier: Development Status :: 5 - Production/Stable
Classifier: Intended Audience :: Developers
Classifier: Operating System :: OS Independent
Classifier: Programming Language :: Python :: 3
Classifier: Programming Language :: Python :: 3.8
Classifier: Programming Language :: Python :: 3.9
Classifier: Programming Language :: Python :: 3.10
Classifier: Programming Language :: Python :: 3.11
Classifier: Programming Language :: Python :: 3.12
Classifier: License :: OSI Approved :: MIT License
Classifier: Topic :: Software Development :: Libraries :: Python Modules
Requires-Python: >=3.8
License-File: LICENSE
Requires-Dist: bitarray<3.0.0,>=2.9.0
